onedep/__init__.py
onedep/api/Register.py
onedep/api/Validate.py
onedep/api/__init__.py
onedep/cli/__init__.py
onedep/cli/validate_cli.py
onedep/utils/ApiBase.py
onedep/utils/__init__.py
onedep_api-0.19.dist-info/LICENSE
onedep_api-0.19.dist-info/METADATA
onedep_api-0.19.dist-info/WHEEL
onedep_api-0.19.dist-info/entry_points.txt
onedep_api-0.19.dist-info/top_level.txt
onedep_api-0.19.dist-info/RECORD
